{"region_id": "RBAS", "operating_unit_email": "registry.so@undp.org", "outputs": [{"output_id": "00014775", "crs": null, "donor_id": ["00187"], "disbursement": [0.0], "focus_area": "-", "gender_descr": "Gender Equality", "output_title": "RRIDP  IN SOMALIA", "budget": [0.0], "fiscal_year": [2012], "gender_id": "1", "expenditure": [-2722.0], "award_id": "00014775", "output_descr": "REINTEGRATION OF RETURNEES AND INTERNALLY DISPLACED PERSONS IN SOMALIA", "donor_short": ["NOR"], "donor_name": ["GOVERNMENT OF NORWAY"], "expense": [-2722.0], "crs_descr": null, "focus_area_descr": "-"}], "operating_unit": "Somalia", "fiscal_year": [2012], "inst_id": "", "project_descr": "REINTEGRATION OF RETURNEES AND INTERNALLY DISPLACED PERSONS IN SOMALIA", "operating_unit_id": "SOM", "expenditure": -2722.0, "iati_op_id": "SO", "document_name": [], "project_id": "00014775", "disbursement": 0.0, "end": "2015-12-31", "project_title": "rridp  in somalia", "subnational": [], "budget": 0.0, "inst_descr": null, "start": "2001-07-01", "operating_unit_website": null, "expense": -2722.0, "inst_type_id": ""}