{"region_id": "RBAP", "operating_unit_email": "registry.cn@undp.org", "outputs": [{"output_id": "00044355", "crs": null, "donor_id": ["00061"], "disbursement": [0.0], "focus_area": "-", "gender_descr": "Gender Equality", "output_title": "Umbrella - Rule of Law", "budget": [473.0], "fiscal_year": [2012], "gender_id": "1", "expenditure": [461.0], "award_id": "00039509", "output_descr": "- to respond in a quick and flexible way to the emerging needs of legal reforms\n- to further enhance the capacity of the nation to develop the rule of law and accessible justice in line with international standards.", "donor_short": ["BEL"], "donor_name": ["GOVERNMENT OF BELGIUM"], "expense": [461.0], "crs_descr": null, "focus_area_descr": "-"}], "operating_unit": "China", "fiscal_year": [2012], "inst_id": "00842", "project_descr": "Umbrella programme to support promotion of rule of law through institutional capacity building and legislation reforms", "operating_unit_id": "CHN", "expenditure": 461.0, "iati_op_id": "CN", "document_name": [["00039509_PRODOC"], ["https://info.undp.org/docs/pdc/Documents/CHN/00039509_PRODOC.pdf"], ["pdf"], [0]], "project_id": "00039509", "disbursement": 0.0, "end": "2009-12-31", "project_title": "umbrella programme to support promotion of rule of law", "subnational": [{"outputID": "00044355", "output_locID": "00044355-1", "name": "China", "focus_area": "-", "lat": "35.000000", "type": "PCLI", "awardID": "00039509", "lon": "105.000000", "precision": "1", "focus_area_descr": "-"}], "budget": 473.0, "inst_descr": "China International Centre For", "start": "2005-04-03", "operating_unit_website": null, "expense": 461.0, "inst_type_id": "10"}