{"region_id": "RBAP", "operating_unit_email": "registry.id@undp.org", "outputs": [{"output_id": "00063310", "crs": "15110", "donor_id": [""], "disbursement": [0.0], "focus_area": "-", "gender_descr": "None", "output_title": "GEP-WRI RAISING THE PROFILE (G", "budget": [0.0], "fiscal_year": [2011], "gender_id": "0", "expenditure": [-3006.0], "award_id": "00051021", "output_descr": "(The Gender Equity and Women's Rights in Indonesia: Raising the Profile project: aims to explore popular perceptions of women's rights and gender equity issues in Indonesia", "donor_short": [], "donor_name": ["UNITED NATIONS DEVELOPMENT PROGRAMME"], "expense": [-3006.0], "crs_descr": "Economic and development policy/planning", "focus_area_descr": "-"}], "operating_unit": "Indonesia", "fiscal_year": [2011], "inst_id": "", "project_descr": "GEP-WRI Raising the Profile (Gender Equality and Promotion of Women's Right the Profile)", "operating_unit_id": "IDN", "expenditure": -3006.0, "iati_op_id": "ID", "document_name": [[], ["http://www.undp.org/content/dam/undp/documents/projects/IDN/00051021/ProDoc-GEPWRI 24September 2008_Award 51021.doc"], [""], [8]], "project_id": "00051021", "disbursement": 0.0, "end": "2010-12-31", "project_title": "gep-wri raising the profile (gender project)", "subnational": [], "budget": 0.0, "inst_descr": "UNDP", "start": "2008-10-01", "operating_unit_website": "http://www.undp.or.id/", "expense": -3006.0, "inst_type_id": "40"}