{"region_id": "RBAP", "operating_unit_email": null, "outputs": [{"output_id": "00061985", "crs": "99810", "donor_id": [""], "disbursement": [0.0], "focus_area": "-", "gender_descr": "None", "output_title": "Strengthen Ministry of Env.", "budget": [0.0], "fiscal_year": [2011], "gender_id": "0", "expenditure": [2519.0], "award_id": "00050258", "output_descr": "Policies and legislations for sustainable environmental management developed and incorporated in national plans including increased capacity for improved implementation of environment programmes.", "donor_short": [], "donor_name": ["UNITED NATIONS DEVELOPMENT PROGRAMME"], "expense": [2519.0], "crs_descr": "Sectors Not Specified", "focus_area_descr": "-"}], "operating_unit": "Solomon Islands", "fiscal_year": [2011], "inst_id": "", "project_descr": "Policies and legislations for sustainable environmental management developed and incorporated in national plans including increased capacity for improved implementation of environment programmes.", "operating_unit_id": "SLB", "expenditure": 2519.0, "iati_op_id": "SB", "document_name": [], "project_id": "00050258", "disbursement": 0.0, "end": "2009-06-30", "project_title": "strengthen ministry of environment", "subnational": [], "budget": 0.0, "inst_descr": "", "start": "2008-06-11", "operating_unit_website": null, "expense": 2519.0, "inst_type_id": ""}