{"region_id": "RBAS", "operating_unit_email": "registry.ma@undp.org", "outputs": [{"output_id": "00083958", "crs": "23010", "donor_id": ["00172", "10003"], "disbursement": [0.0, 0.0], "focus_area": "1", "gender_descr": "Gender Equality", "output_title": "PIMS5079:PPG Circular Economy", "budget": [175000.0, 61541.0], "fiscal_year": [2013, 2014], "gender_id": "1", "expenditure": [103150.0, 57211.0], "award_id": "00069313", "output_descr": "Circular Economy in Souss Massa Draa Region", "donor_short": ["MOR", "GEFTrustee"], "donor_name": ["GOVERNMENT OF MOROCCO", "Global Environment Fund Truste"], "expense": [103150.0, 57211.0], "crs_descr": null, "focus_area_descr": "Inclusive & Sustainable Growth"}], "operating_unit": "Morocco", "fiscal_year": [2014, 2013], "inst_id": "99999", "project_descr": "Circular Economy in Souss Massa Draa Region", "operating_unit_id": "MAR", "expenditure": 160361.0, "iati_op_id": "MA", "document_name": [], "project_id": "00069313", "disbursement": 0.0, "end": "2013-05-31", "project_title": "pims5079:ppg circular economy in souss massa draa region", "subnational": [{"outputID": "00083958", "output_locID": "00083958-1", "name": "Kingdom of Morocco", "focus_area": "1", "lat": "32.000000", "type": "PCLI", "awardID": "00069313", "lon": "-6.000000", "precision": "1", "focus_area_descr": "Inclusive & Sustainable Growth"}], "budget": 236541.0, "inst_descr": "UNDP", "start": "2012-09-01", "operating_unit_website": null, "expense": 160361.0, "inst_type_id": "40"}