{"region_id": "RBLAC", "operating_unit_email": "registry.sr@undp.org", "outputs": [{"output_id": "00090944", "crs": "15170", "donor_id": ["00012"], "disbursement": [0.0, 0.0], "focus_area": "4", "gender_descr": "Gender Equality", "output_title": "Capacity Development MoFA", "budget": [11467.0, 20000.0], "fiscal_year": [2014, 2015], "gender_id": "1", "expenditure": [10884.0, 14229.0], "award_id": "00081774", "output_descr": "The MoFA and the UNDAF PCGs have requested capacity strengthening in the areas of Results Based Management (basic and advanced), Gender Mainstreaming, Gender Analysis and language training to enable them to improve critical skills.", "donor_short": ["UNDP"], "donor_name": ["Voluntary Contributions"], "expense": [10884.0, 14229.0], "crs_descr": null, "focus_area_descr": "Gender Equality"}], "operating_unit": "Suriname", "fiscal_year": [2015, 2014], "inst_id": "00002", "project_descr": "This Initiation Plan aims to give technical support to the process of capacity development of the Ministry of Foreign Affairs and through this Ministry to the Programme Coordination Groups (PCGs).", "operating_unit_id": "SUR", "expenditure": 25113.0, "iati_op_id": "SR", "document_name": [["Request for Procurement"], ["http://procurement-notices.undp.org/index.cfm"], [""], [10]], "project_id": "00081774", "disbursement": 0.0, "end": "2015-07-01", "project_title": "ip capacity development mofa", "subnational": [], "budget": 31467.0, "inst_descr": "Ministry of Foreign  Affairs", "start": "2014-07-01", "operating_unit_website": null, "expense": 25113.0, "inst_type_id": "10"}