{"region_id": "RBLAC", "operating_unit_email": "registry.do@undp.org", "outputs": [{"output_id": "00091140", "crs": "15113", "donor_id": ["00098"], "disbursement": [0.0, 0.0], "focus_area": "2", "gender_descr": "Gender Equality", "output_title": "TRAMITE REGULAR ESTRUCTURADO", "budget": [107200.0, 86237.0], "fiscal_year": [2014, 2015], "gender_id": "1", "expenditure": [0.0, 0.0], "award_id": "00082062", "output_descr": "La Contraloria cuenta con el modulo de Tramite Regular Estructurado del SIGOB (TRE) instalado y en funcionamiento", "donor_short": ["DOM"], "donor_name": ["GOVERNMENT OF DOMINICAN REPUBLIC"], "expense": [0.0, 0.0], "crs_descr": null, "focus_area_descr": "Democratic Governance"}], "operating_unit": "Dominican Republic", "fiscal_year": [2015, 2014], "inst_id": "00923", "project_descr": "El objetivo del proyecto es fortalecer las capacidades de la Contraloria a traves de un sistema de gestion de Tramite Regular Estructurado (TRE)", "operating_unit_id": "DOM", "expenditure": 0.0, "iati_op_id": "DO", "document_name": [["prodoc 2014", "pnud_do_progpais12-16", "Request for Procurement"], ["https://info.undp.org/docs/pdc/Documents/DOM/Documento de Proyecto 2014.pdf", "http://www.do.undp.org/content/dam/dominican_republic/docs/marcolegal/pnud_do_progpais12-16.pdf", "http://procurement-notices.undp.org/index.cfm"], ["pdf", "pdf", ""], [0, 7, 10]], "project_id": "00082062", "disbursement": 0.0, "end": "2015-12-31", "project_title": "tramite regular estructurado contraloria", "subnational": [], "budget": 193437.0, "inst_descr": "Gobierno Republica Dominicana", "start": "2014-07-02", "operating_unit_website": null, "expense": 0.0, "inst_type_id": "10"}